tts_plugin_mozilla_remote/__init__.py
tts_plugin_mozilla_remote/version.py
tts_plugin_mozilla_remote-3.0.0.dist-info/LICENSE.md
tts_plugin_mozilla_remote-3.0.0.dist-info/METADATA
tts_plugin_mozilla_remote-3.0.0.dist-info/WHEEL
tts_plugin_mozilla_remote-3.0.0.dist-info/entry_points.txt
tts_plugin_mozilla_remote-3.0.0.dist-info/top_level.txt
tts_plugin_mozilla_remote-3.0.0.dist-info/RECORD
