Metadata-Version: 2.2
Name: tts-plugin-mozilla_remote
Version: 3.0.0
Summary: A Mozilla/Coqui TTS plugin for Neon and OVOS
Author-email: Neongecko/Oscillate Labs <mike@oscillatelabs.net>
License: BSD-3-Clause
Project-URL: Homepage, https://github.com/OscillateLabsLLC/tts-plugin-mozilla_remote
Keywords: mycroft,ovos,neon,plugin,tts
Classifier: Intended Audience :: Developers
Classifier: Topic :: Text Processing :: Linguistic
Classifier: Programming Language :: Python :: 3
Requires-Python: >=3.9
License-File: LICENSE.md
Requires-Dist: ovos-plugin-manager
Requires-Dist: requests
Requires-Dist: setuptools
Provides-Extra: test
Requires-Dist: ovos-core; extra == "test"
Requires-Dist: pytest; extra == "test"
